setup.py
cmpa/__init__.py
cmpa/__version__.py
cmpa/cmpa.py
cmpa.egg-info/PKG-INFO
cmpa.egg-info/SOURCES.txt
cmpa.egg-info/dependency_links.txt
cmpa.egg-info/top_level.txt