Metadata-Version: 1.1
Name: cmpa
Version: 0.0.4
Summary: Comparison utility
Home-page: https://github.com/jamesabel/cmpa
Author: James Abel
Author-email: j@abel.co
License: MIT License
Download-URL: https://github.com/jamesabel/cmpa/archive/master.zip
Keywords: directory,file,comparison,utility
Platform: UNKNOWN
